dgml_utils/__init__.py
dgml_utils/cli.py
dgml_utils/config.py
dgml_utils/conversions.py
dgml_utils/locators.py
dgml_utils/models.py
dgml_utils/py.typed
dgml_utils/segmentation.py
dgml_utils-0.3.4.dist-info/METADATA
dgml_utils-0.3.4.dist-info/WHEEL
dgml_utils-0.3.4.dist-info/entry_points.txt
dgml_utils-0.3.4.dist-info/RECORD
